<?xml version="1.0" encoding="UTF-8"?>

<!-- generated on 2025-09-07 20:44:57 by Eclipse SUMO netconvert Version 1.18.0
<configuration xmlns:xsi="http://www.w3.org/2001/XMLSchema-instance" xsi:noNamespaceSchemaLocation="http://sumo.dlr.de/xsd/netconvertConfiguration.xsd">

    <input>
        <node-files value="data/nodes.xml"/>
        <edge-files value="data/edges.xml"/>
        <connection-files value="data/connections.xml"/>
    </input>

    <output>
        <output-file value="data/net.xml"/>
    </output>

    <report>
        <verbose value="true"/>
    </report>

</configuration>
-->

<net version="1.16" junctionCornerDetail="5" limitTurnSpeed="5.50" xmlns:xsi="http://www.w3.org/2001/XMLSchema-instance" xsi:noNamespaceSchemaLocation="http://sumo.dlr.de/xsd/net_file.xsd">

    <location netOffset="100.00,0.00" convBoundary="0.00,0.00,200.00,100.00" origBoundary="-100.00,0.00,100.00,100.00" projParameter="!"/>

    <edge id=":E_0" function="internal">
        <lane id=":E_0_0" index="0" speed="12.73" length="15.02" shape="132.13,4.80 129.60,5.29 126.67,6.76 123.35,9.20 119.64,12.62"/>
    </edge>
    <edge id=":E_1" function="internal">
        <lane id=":E_1_0" index="0" speed="13.89" length="17.05" shape="132.13,4.80 115.07,4.80"/>
        <lane id=":E_1_1" index="1" speed="13.89" length="17.05" shape="132.13,1.60 115.07,1.60"/>
    </edge>
    <edge id=":E_3" function="internal">
        <lane id=":E_3_0" index="0" speed="13.89" length="17.05" shape="115.07,-4.80 132.13,-4.80"/>
        <lane id=":E_3_1" index="1" speed="13.89" length="17.05" shape="115.07,-1.60 132.13,-1.60"/>
    </edge>
    <edge id=":E_5" function="internal">
        <lane id=":E_5_0" index="0" speed="13.89" length="19.92" shape="117.38,10.36 119.84,7.00 122.52,3.05 126.31,-0.23 132.13,-1.60"/>
    </edge>
    <edge id=":J0_0" function="internal">
        <lane id=":J0_0_0" index="0" speed="6.51" length="9.03" shape="95.20,10.40 94.85,7.95 93.80,6.20 92.05,5.15 89.60,4.80"/>
        <lane id=":J0_0_1" index="1" speed="8.00" length="14.19" shape="98.40,10.40 97.85,6.55 96.20,3.80 93.45,2.15 89.60,1.60"/>
    </edge>
    <edge id=":J0_2" function="internal">
        <lane id=":J0_2_0" index="0" speed="9.26" length="19.35" shape="98.40,10.40 99.15,5.15 101.40,1.40 105.15,-0.85 110.40,-1.60"/>
    </edge>
    <edge id=":J0_3" function="internal">
        <lane id=":J0_3_0" index="0" speed="6.51" length="9.03" shape="110.40,4.80 107.95,5.15 106.20,6.20 105.15,7.95 104.80,10.40"/>
    </edge>
    <edge id=":J0_4" function="internal">
        <lane id=":J0_4_0" index="0" speed="13.89" length="20.80" shape="110.40,4.80 89.60,4.80"/>
        <lane id=":J0_4_1" index="1" speed="13.89" length="20.80" shape="110.40,1.60 89.60,1.60"/>
    </edge>
    <edge id=":J0_6" function="internal">
        <lane id=":J0_6_0" index="0" speed="13.89" length="20.80" shape="89.60,-4.80 110.40,-4.80"/>
        <lane id=":J0_6_1" index="1" speed="13.89" length="20.80" shape="89.60,-1.60 110.40,-1.60"/>
    </edge>
    <edge id=":J0_8" function="internal">
        <lane id=":J0_8_0" index="0" speed="9.26" length="5.01" shape="89.60,-1.60 94.56,-0.89"/>
    </edge>
    <edge id=":J0_9" function="internal">
        <lane id=":J0_9_0" index="0" speed="9.26" length="14.34" shape="94.56,-0.89 94.85,-0.85 98.60,1.40 100.85,5.15 101.60,10.40"/>
    </edge>
    <edge id=":N_0" function="internal">
        <lane id=":N_0_0" index="0" speed="13.89" length="17.05" shape="95.20,32.13 95.20,15.07"/>
        <lane id=":N_0_1" index="1" speed="13.89" length="17.05" shape="98.40,32.13 98.40,15.07"/>
    </edge>
    <edge id=":N_2" function="internal">
        <lane id=":N_2_0" index="0" speed="13.89" length="2.10" shape="98.40,32.13 99.15,30.16"/>
    </edge>
    <edge id=":N_7" function="internal">
        <lane id=":N_7_0" index="0" speed="13.89" length="17.03" shape="99.15,30.16 101.39,27.04 105.13,22.78 110.36,17.38"/>
    </edge>
    <edge id=":N_3" function="internal">
        <lane id=":N_3_0" index="0" speed="12.73" length="15.02" shape="112.62,19.64 109.20,23.35 106.76,26.67 105.29,29.60 104.80,32.13"/>
        <lane id=":N_3_1" index="1" speed="13.41" length="16.71" shape="112.62,19.64 107.80,24.55 104.36,28.27 102.29,30.80 101.60,32.13"/>
    </edge>
    <edge id=":N_5" function="internal">
        <lane id=":N_5_0" index="0" speed="13.89" length="17.05" shape="104.80,15.07 104.80,32.13"/>
        <lane id=":N_5_1" index="1" speed="13.89" length="17.05" shape="101.60,15.07 101.60,32.13"/>
    </edge>

    <edge id="C1" from="N" to="E" priority="-1">
        <lane id="C1_0" index="0" speed="13.89" length="9.92" shape="110.36,17.38 117.38,10.36"/>
    </edge>
    <edge id="C2" from="E" to="N" priority="-1">
        <lane id="C2_0" index="0" speed="13.89" length="9.92" shape="119.64,12.62 112.62,19.64"/>
    </edge>
    <edge id="E1_in" from="E1" to="E" priority="-1">
        <lane id="E1_in_0" index="0" speed="13.89" length="67.87" shape="200.00,4.80 132.13,4.80"/>
        <lane id="E1_in_1" index="1" speed="13.89" length="67.87" shape="200.00,1.60 132.13,1.60"/>
    </edge>
    <edge id="E1_out" from="E" to="E1" priority="-1">
        <lane id="E1_out_0" index="0" speed="13.89" length="67.87" shape="132.13,-4.80 200.00,-4.80"/>
        <lane id="E1_out_1" index="1" speed="13.89" length="67.87" shape="132.13,-1.60 200.00,-1.60"/>
    </edge>
    <edge id="E_in" from="E" to="J0" priority="-1">
        <lane id="E_in_0" index="0" speed="13.89" length="4.67" shape="115.07,4.80 110.40,4.80"/>
        <lane id="E_in_1" index="1" speed="13.89" length="4.67" shape="115.07,1.60 110.40,1.60"/>
    </edge>
    <edge id="E_out" from="J0" to="E" priority="-1">
        <lane id="E_out_0" index="0" speed="13.89" length="4.67" shape="110.40,-4.80 115.07,-4.80"/>
        <lane id="E_out_1" index="1" speed="13.89" length="4.67" shape="110.40,-1.60 115.07,-1.60"/>
    </edge>
    <edge id="N1_in" from="N1" to="N" priority="-1">
        <lane id="N1_in_0" index="0" speed="13.89" length="67.87" shape="95.20,100.00 95.20,32.13"/>
        <lane id="N1_in_1" index="1" speed="13.89" length="67.87" shape="98.40,100.00 98.40,32.13"/>
    </edge>
    <edge id="N1_out" from="N" to="N1" priority="-1">
        <lane id="N1_out_0" index="0" speed="13.89" length="67.87" shape="104.80,32.13 104.80,100.00"/>
        <lane id="N1_out_1" index="1" speed="13.89" length="67.87" shape="101.60,32.13 101.60,100.00"/>
    </edge>
    <edge id="N_in" from="N" to="J0" priority="-1">
        <lane id="N_in_0" index="0" speed="13.89" length="4.67" shape="95.20,15.07 95.20,10.40"/>
        <lane id="N_in_1" index="1" speed="13.89" length="4.67" shape="98.40,15.07 98.40,10.40"/>
    </edge>
    <edge id="N_out" from="J0" to="N" priority="-1">
        <lane id="N_out_0" index="0" speed="13.89" length="4.67" shape="104.80,10.40 104.80,15.07"/>
        <lane id="N_out_1" index="1" speed="13.89" length="4.67" shape="101.60,10.40 101.60,15.07"/>
    </edge>
    <edge id="W_in" from="W" to="J0" priority="-1">
        <lane id="W_in_0" index="0" speed="13.89" length="89.60" shape="0.00,-4.80 89.60,-4.80"/>
        <lane id="W_in_1" index="1" speed="13.89" length="89.60" shape="0.00,-1.60 89.60,-1.60"/>
    </edge>
    <edge id="W_out" from="J0" to="W" priority="-1">
        <lane id="W_out_0" index="0" speed="13.89" length="89.60" shape="89.60,4.80 0.00,4.80"/>
        <lane id="W_out_1" index="1" speed="13.89" length="89.60" shape="89.60,1.60 0.00,1.60"/>
    </edge>

    <tlLogic id="J0" type="static" programID="0" offset="0">
        <phase duration="42" state="rrrGGGGGg"/>
        <phase duration="3"  state="rrryyyyyy"/>
        <phase duration="42" state="GGGGrrrrr"/>
        <phase duration="3"  state="yyyyrrrrr"/>
    </tlLogic>

    <junction id="E" type="priority" x="130.00" y="0.00" incLanes="E1_in_0 E1_in_1 E_out_0 E_out_1 C1_0" intLanes=":E_0_0 :E_1_0 :E_1_1 :E_3_0 :E_3_1 :E_5_0" shape="132.13,6.40 132.13,-6.40 115.07,-6.40 115.07,6.40 116.98,6.71 117.37,7.11 117.37,7.66 117.00,8.36 116.25,9.23 120.77,13.75 123.13,11.51 125.30,9.67 127.29,8.24 129.09,7.22 130.70,6.60">
        <request index="0" response="000000" foes="000000" cont="0"/>
        <request index="1" response="000000" foes="100000" cont="0"/>
        <request index="2" response="000000" foes="100000" cont="0"/>
        <request index="3" response="000000" foes="100000" cont="0"/>
        <request index="4" response="000000" foes="100000" cont="0"/>
        <request index="5" response="011110" foes="011110" cont="0"/>
    </junction>
    <junction id="E1" type="dead_end" x="200.00" y="0.00" incLanes="E1_out_0 E1_out_1" intLanes="" shape="200.00,0.00 200.00,-6.40 200.00,0.00"/>
    <junction id="J0" type="traffic_light" x="100.00" y="0.00" incLanes="N_in_0 N_in_1 E_in_0 E_in_1 W_in_0 W_in_1" intLanes=":J0_0_0 :J0_0_1 :J0_2_0 :J0_3_0 :J0_4_0 :J0_4_1 :J0_6_0 :J0_6_1 :J0_9_0" shape="93.60,10.40 106.40,10.40 106.84,8.18 107.40,7.40 108.18,6.84 109.18,6.51 110.40,6.40 110.40,-6.40 89.60,-6.40 89.60,6.40 91.82,6.84 92.60,7.40 93.16,8.18 93.49,9.18">
        <request index="0" response="000110000" foes="000110000" cont="0"/>
        <request index="1" response="000110000" foes="000110000" cont="0"/>
        <request index="2" response="111110000" foes="111110000" cont="0"/>
        <request index="3" response="000000000" foes="000000000" cont="0"/>
        <request index="4" response="000000000" foes="100000111" cont="0"/>
        <request index="5" response="000000000" foes="100000111" cont="0"/>
        <request index="6" response="000000000" foes="000000100" cont="0"/>
        <request index="7" response="000000000" foes="000000100" cont="0"/>
        <request index="8" response="000110000" foes="000110100" cont="1"/>
    </junction>
    <junction id="N" type="priority" x="100.00" y="30.00" incLanes="N1_in_0 N1_in_1 C2_0 N_out_0 N_out_1" intLanes=":N_0_0 :N_0_1 :N_7_0 :N_3_0 :N_3_1 :N_5_0 :N_5_1" shape="93.60,32.13 106.40,32.13 106.61,29.27 107.24,27.24 108.28,25.71 109.72,24.34 111.55,22.80 113.75,20.77 109.23,16.25 107.66,17.37 107.11,17.37 106.71,16.98 106.48,16.22 106.40,15.07 93.60,15.07">
        <request index="0" response="0000000" foes="0000000" cont="0"/>
        <request index="1" response="0000000" foes="0000000" cont="0"/>
        <request index="2" response="1100000" foes="1100000" cont="1"/>
        <request index="3" response="1100000" foes="1100000" cont="0"/>
        <request index="4" response="1100000" foes="1100000" cont="0"/>
        <request index="5" response="0000000" foes="0011100" cont="0"/>
        <request index="6" response="0000000" foes="0011100" cont="0"/>
    </junction>
    <junction id="N1" type="dead_end" x="100.00" y="100.00" incLanes="N1_out_0 N1_out_1" intLanes="" shape="100.00,100.00 106.40,100.00 100.00,100.00"/>
    <junction id="W" type="dead_end" x="0.00" y="0.00" incLanes="W_out_0 W_out_1" intLanes="" shape="0.00,0.00 0.00,6.40 0.00,0.00"/>

    <junction id=":J0_9_0" type="internal" x="94.56" y="-0.89" incLanes=":J0_8_0 E_in_0 E_in_1" intLanes=":J0_2_0 :J0_4_0 :J0_4_1"/>
    <junction id=":N_7_0" type="internal" x="99.15" y="30.16" incLanes=":N_2_0 N_out_0 N_out_1" intLanes=":N_5_0 :N_5_1"/>

    <connection from="C1" to="E1_out" fromLane="0" toLane="1" via=":E_5_0" dir="l" state="m"/>
    <connection from="C2" to="N1_out" fromLane="0" toLane="0" via=":N_3_0" dir="r" state="m"/>
    <connection from="C2" to="N1_out" fromLane="0" toLane="1" via=":N_3_1" dir="r" state="m"/>
    <connection from="E1_in" to="C2" fromLane="0" toLane="0" via=":E_0_0" dir="r" state="M"/>
    <connection from="E1_in" to="E_in" fromLane="0" toLane="0" via=":E_1_0" dir="s" state="M"/>
    <connection from="E1_in" to="E_in" fromLane="1" toLane="1" via=":E_1_1" dir="s" state="M"/>
    <connection from="E_in" to="N_out" fromLane="0" toLane="0" via=":J0_3_0" tl="J0" linkIndex="3" dir="r" state="O"/>
    <connection from="E_in" to="W_out" fromLane="0" toLane="0" via=":J0_4_0" tl="J0" linkIndex="4" dir="s" state="O"/>
    <connection from="E_in" to="W_out" fromLane="1" toLane="1" via=":J0_4_1" tl="J0" linkIndex="5" dir="s" state="O"/>
    <connection from="E_out" to="E1_out" fromLane="0" toLane="0" via=":E_3_0" dir="s" state="M"/>
    <connection from="E_out" to="E1_out" fromLane="1" toLane="1" via=":E_3_1" dir="s" state="M"/>
    <connection from="N1_in" to="N_in" fromLane="0" toLane="0" via=":N_0_0" dir="s" state="M"/>
    <connection from="N1_in" to="N_in" fromLane="1" toLane="1" via=":N_0_1" dir="s" state="M"/>
    <connection from="N1_in" to="C1" fromLane="1" toLane="0" via=":N_2_0" dir="l" state="m"/>
    <connection from="N_in" to="W_out" fromLane="0" toLane="0" via=":J0_0_0" tl="J0" linkIndex="0" dir="r" state="o"/>
    <connection from="N_in" to="W_out" fromLane="1" toLane="1" via=":J0_0_1" tl="J0" linkIndex="1" dir="r" state="o"/>
    <connection from="N_in" to="E_out" fromLane="1" toLane="1" via=":J0_2_0" tl="J0" linkIndex="2" dir="l" state="o"/>
    <connection from="N_out" to="N1_out" fromLane="0" toLane="0" via=":N_5_0" dir="s" state="M"/>
    <connection from="N_out" to="N1_out" fromLane="1" toLane="1" via=":N_5_1" dir="s" state="M"/>
    <connection from="W_in" to="E_out" fromLane="0" toLane="0" via=":J0_6_0" tl="J0" linkIndex="6" dir="s" state="O"/>
    <connection from="W_in" to="E_out" fromLane="1" toLane="1" via=":J0_6_1" tl="J0" linkIndex="7" dir="s" state="O"/>
    <connection from="W_in" to="N_out" fromLane="1" toLane="1" via=":J0_8_0" tl="J0" linkIndex="8" dir="l" state="o"/>

    <connection from=":E_0" to="C2" fromLane="0" toLane="0" dir="r" state="M"/>
    <connection from=":E_1" to="E_in" fromLane="0" toLane="0" dir="s" state="M"/>
    <connection from=":E_1" to="E_in" fromLane="1" toLane="1" dir="s" state="M"/>
    <connection from=":E_3" to="E1_out" fromLane="0" toLane="0" dir="s" state="M"/>
    <connection from=":E_3" to="E1_out" fromLane="1" toLane="1" dir="s" state="M"/>
    <connection from=":E_5" to="E1_out" fromLane="0" toLane="1" dir="l" state="M"/>
    <connection from=":J0_0" to="W_out" fromLane="0" toLane="0" dir="r" state="M"/>
    <connection from=":J0_0" to="W_out" fromLane="1" toLane="1" dir="r" state="M"/>
    <connection from=":J0_2" to="E_out" fromLane="0" toLane="1" dir="l" state="M"/>
    <connection from=":J0_3" to="N_out" fromLane="0" toLane="0" dir="r" state="M"/>
    <connection from=":J0_4" to="W_out" fromLane="0" toLane="0" dir="s" state="M"/>
    <connection from=":J0_4" to="W_out" fromLane="1" toLane="1" dir="s" state="M"/>
    <connection from=":J0_6" to="E_out" fromLane="0" toLane="0" dir="s" state="M"/>
    <connection from=":J0_6" to="E_out" fromLane="1" toLane="1" dir="s" state="M"/>
    <connection from=":J0_8" to="N_out" fromLane="0" toLane="1" via=":J0_9_0" dir="l" state="m"/>
    <connection from=":J0_9" to="N_out" fromLane="0" toLane="1" dir="l" state="M"/>
    <connection from=":N_0" to="N_in" fromLane="0" toLane="0" dir="s" state="M"/>
    <connection from=":N_0" to="N_in" fromLane="1" toLane="1" dir="s" state="M"/>
    <connection from=":N_2" to="C1" fromLane="0" toLane="0" via=":N_7_0" dir="l" state="m"/>
    <connection from=":N_7" to="C1" fromLane="0" toLane="0" dir="l" state="M"/>
    <connection from=":N_3" to="N1_out" fromLane="0" toLane="0" dir="r" state="M"/>
    <connection from=":N_3" to="N1_out" fromLane="1" toLane="1" dir="r" state="M"/>
    <connection from=":N_5" to="N1_out" fromLane="0" toLane="0" dir="s" state="M"/>
    <connection from=":N_5" to="N1_out" fromLane="1" toLane="1" dir="s" state="M"/>

</net>
